nepse_client/__init__.py
nepse_client/async_client.py
nepse_client/client.py
nepse_client/dummy_id_manager.py
nepse_client/exceptions.py
nepse_client/py.typed
nepse_client/sync_client.py
nepse_client/token_manager.py
nepse_client/data/API_ENDPOINTS.json
nepse_client/data/DUMMY_DATA.json
nepse_client/data/HEADERS.json
nepse_client/data/USER_AGENTS.json
nepse_client/data/css.wasm
nepse_client-0.1.4.dist-info/licenses/LICENSE
nepse_client-0.1.4.dist-info/METADATA
nepse_client-0.1.4.dist-info/WHEEL
nepse_client-0.1.4.dist-info/top_level.txt
nepse_client-0.1.4.dist-info/RECORD
