Metadata-Version: 2.4
Name: nepse-client
Version: 0.1.4
Summary: A comprehensive Python client for Nepal Stock Exchange (NEPSE) API
Author-email: Amrit Giri <amritgiri.dev@gmail.com>
License: MIT
Project-URL: Homepage, https://github.com/4mritgiri/NepseClient
Project-URL: Bug Reports, https://github.com/4mritgiri/NepseClient/issues
Project-URL: Source, https://github.com/4mritgiri/NepseClient
Project-URL: Documentation, https://NepseClient.readthedocs.io
Keywords: NEPSE,nepal,stock,exchange,finance,trading,api,client
Classifier: Development Status :: 4 - Beta
Classifier: Intended Audience :: Developers
Classifier: Intended Audience :: Financial and Insurance Industry
Classifier: Topic :: Office/Business :: Financial :: Investment
Classifier: License :: OSI Approved :: MIT License
Classifier: Programming Language :: Python :: 3
Classifier: Programming Language :: Python :: 3.11
Classifier: Programming Language :: Python :: 3.12
Classifier: Programming Language :: Python :: 3.13
Classifier: Programming Language :: Python :: 3.14
Classifier: Operating System :: OS Independent
Classifier: Typing :: Typed
Requires-Python: >=3.11
License-File: LICENSE
Requires-Dist: httpx[http2]>=0.24.0
Requires-Dist: pywasm>=1.0.8
Requires-Dist: tqdm>=4.65.0
Dynamic: license-file
